<?xml version="1.0" encoding="UTF-8"?>
<dirfilms>
    <dirid>AA</dirid>
    <is>Asquith</is>
    <castnote>Actors and notes.</castnote>
    <filmc>
        <m>
            <f>AA13</f>
            <t>Pygmalion</t>
            <a>Leslie Howard</a>
            <p>Sci</p>
            <r>smug professor</r>
            <n>Higgins</n>
            <awards>
                <award>AAN</award>
            </awards>
        </m>
        <m>
            <f>AA13</f>
            <t>Pygmalion</t>
            <a>Wendy Hiller</a>
            <p>Inn</p>
            <r>flower girl</r>
            <n>Eliza</n>
            <awards>
                <award>AAN</award>
            </awards>
        </m>
        <m>
            <f>AA13</f>
            <t>Pygmalion</t>
            <a>Wilfrid Lawson</a>
            <p>Sdk</p>
            <r>Eliza's father</r>
            <n>Dolittle</n>
        </m>
        <m>
            <f>AA13</f>
            <t>Pygmalion</t>
            <a>Scott Sunderland</a>
            <p>Und</p>
            <r>betting Colonel</r>
            <n>Pickering</n>
        </m>
        <m>
            <f>AA13</f>
            <t>Pygmalion</t>
            <a>Marie Lohr</a>
            <p>Und</p>
            <r/>
            <n>Mrs.Higgins</n>
        </m>
        <m>
            <f>AA13</f>
            <t>Pygmalion</t>
            <a>Iris Hoey</a>
            <p>Und</p>
            <r/>
        </m>
        <m>
            <f>AA13</f>
            <t>Pygmalion</t>
            <a>David Tree</a>
            <p>Und</p>
            <r>fop</r>
            <n>Freddie Eynsford-Hill</n>
        </m>
        <m>
            <f>AA13</f>
            <t>Pygmalion</t>
            <a>Esme Percy</a>
            <p>Und</p>
            <r/>
        </m>
        <m>
            <f>AA13</f>
            <t>Pygmalion</t>
            <a>Everley Gregg</a>
            <p>Und</p>
            <r/>
        </m>
        <m>
            <f>AA13</f>
            <t>Pygmalion</t>
            <a>O.B. Clarence</a>
            <p>Und</p>
            <r/>
        </m>
        <m>
            <f>AA13</f>
            <t>Pygmalion</t>
            <a>Jean Cadell</a>
            <p>Und</p>
            <r/>
        </m>
    </filmc>
    <filmc>
        <m>
            <f>AA14</f>
            <t>French Without Tears</t>
            <a>Ray Milland</a>
            <p>Und</p>
            <r>schoolboy</r>
            <error>R(An)</error>
        </m>
        <m>
            <f>AA14</f>
            <t>French Without Tears</t>
            <a>Ellen Drew</a>
            <p>Und</p>
            <r>teacher</r>
        </m>
        <m>
            <f>AA14</f>
            <t>French Without Tears</t>
            <a>Guy Middleton</a>
            <p>Und</p>
            <r>schoolboy</r>
        </m>
        <m>
            <f>AA14</f>
            <t>French Without Tears</t>
            <a>Ronald Culver</a>
            <p>Und</p>
            <r>schoolboy</r>
            <error>Roland</error>
            <error>Sp(An)</error>
        </m>
    </filmc>
    <filmc>
        <m>
            <f>AA16</f>
            <t>Quiet Wedding</t>
            <a>Margaret Lockwood</a>
            <p>Und</p>
            <r>bride</r>
        </m>
        <m>
            <f>AA16</f>
            <t>Quiet Wedding</t>
            <a>Derek Farr</a>
            <p>Und</p>
            <r>bridegroom</r>
        </m>
        <m>
            <f>AA16</f>
            <t>Quiet Wedding</t>
            <a>A.E. Matthews</a>
            <p>Und</p>
            <r/>
        </m>
        <m>
            <f>AA16</f>
            <t>Quiet Wedding</t>
            <a>Marjorie Fielding</a>
            <p>Und</p>
            <r>mother</r>
        </m>
        <m>
            <f>AA16</f>
            <t>Quiet Wedding</t>
            <a>Athene Seyler</a>
            <p>Und</p>
            <r/>
        </m>
        <m>
            <f>AA16</f>
            <t>Quiet Wedding</t>
            <a>Peggy Ashcroft</a>
            <p>Und</p>
            <r/>
        </m>
        <m>
            <f>AA16</f>
            <t>Quiet Wedding</t>
            <a>Margaretta Scott</a>
            <p>Und</p>
            <r/>
        </m>
        <m>
            <f>AA16</f>
            <t>Quiet Wedding</t>
            <a>Bernard Miles</a>
            <p>Und</p>
            <r/>
        </m>
    </filmc>
    <filmc>
        <m>
            <f>AA29</f>
            <t>The Importance of Being Earnest</t>
            <a>Michael Redgrave</a>
            <p>Und</p>
            <r>bachelor</r>
            <n>Earnest</n>
        </m>
        <m>
            <f>AA29</f>
            <t>The Importance of Being Earnest</t>
            <a>Michael Denison</a>
            <p>Und</p>
            <r>bachelor</r>
        </m>
        <m>
            <f>AA29</f>
            <t>The Importance of Being Earnest</t>
            <a>Edith Evans</a>
            <p>Und</p>
            <r>rich daughter</r>
        </m>
        <m>
            <f>AA29</f>
            <t>The Importance of Being Earnest</t>
            <a>Margaret Rurtherford</a>
            <p>Und</p>
            <r/>
        </m>
        <m>
            <f>AA29</f>
            <t>The Importance of Being Earnest</t>
            <a>Joan Greenwood</a>
            <p>Und</p>
            <r/>
        </m>
        <m>
            <f>AA29</f>
            <t>The Importance of Being Earnest</t>
            <a>Miles Malleson</a>
            <p>Und</p>
            <r/>
        </m>
        <m>
            <f>AA29</f>
            <t>The Importance of Being Earnest</t>
            <a>Doroty Tutin</a>
            <p>Und</p>
            <r/>
        </m>
        <m>
            <f>AA29</f>
            <t>The Importance of Being Earnest</t>
            <a>Walter Hudd</a>
            <p>Und</p>
            <r/>
        </m>
    </filmc>
    <filmc>
        <m>
            <f>AA37</f>
            <t>Libel</t>
            <a>Dirk Bogarde</a>
            <p>Und</p>
            <r/>
        </m>
        <m>
            <f>AA37</f>
            <t>Libel</t>
            <a>Olivia deHavilland</a>
            <p>Und</p>
            <r/>
        </m>
        <m>
            <f>AA37</f>
            <t>Libel</t>
            <a>Paul Massie</a>
            <p>Und</p>
            <r/>
        </m>
        <m>
            <f>AA37</f>
            <t>Libel</t>
            <a>Wilfrid Hyde White</a>
            <p>Und</p>
            <r/>
        </m>
        <m>
            <f>AA37</f>
            <t>Libel</t>
            <a>Robert Morley</a>
            <p>Und</p>
            <r/>
        </m>
        <m>
            <f>AA37</f>
            <t>Libel</t>
            <a>Anthony Dawson</a>
            <p>Und</p>
            <r/>
        </m>
        <m>
            <f>AA37</f>
            <t>Libel</t>
            <a>Richard Wattis</a>
            <p>Und</p>
            <r/>
        </m>
        <m>
            <f>AA37</f>
            <t>Libel</t>
            <a>Martin Miller</a>
            <p>Und</p>
            <r/>
        </m>
        <m>
            <f>AA37</f>
            <t>Libel</t>
            <a>Millicent Martin</a>
            <p>Und</p>
            <r/>
        </m>
    </filmc>
</dirfilms>